WrightTools/CITATION
WrightTools/VERSION
WrightTools/WT5_VERSION
WrightTools/__citation__.py
WrightTools/__init__.py
WrightTools/__version__.py
WrightTools/__wt5_version__.py
WrightTools/_close.py
WrightTools/_dataset.py
WrightTools/_group.py
WrightTools/_open.py
WrightTools/exceptions.py
WrightTools/units.py
WrightTools/artists/__init__.py
WrightTools/artists/_base.py
WrightTools/artists/_colors.py
WrightTools/artists/_helpers.py
WrightTools/artists/_interact.py
WrightTools/artists/_quick.py
WrightTools/cli/__init__.py
WrightTools/cli/_units.py
WrightTools/cli/_wt5.py
WrightTools/collection/__init__.py
WrightTools/collection/_cary.py
WrightTools/collection/_collection.py
WrightTools/collection/_directory.py
WrightTools/data/__init__.py
WrightTools/data/_aramis.py
WrightTools/data/_axis.py
WrightTools/data/_brunold.py
WrightTools/data/_channel.py
WrightTools/data/_colors.py
WrightTools/data/_constant.py
WrightTools/data/_data.py
WrightTools/data/_databroker.py
WrightTools/data/_jasco.py
WrightTools/data/_join.py
WrightTools/data/_kent.py
WrightTools/data/_labram.py
WrightTools/data/_ocean_optics.py
WrightTools/data/_pycmds.py
WrightTools/data/_shimadzu.py
WrightTools/data/_solis.py
WrightTools/data/_spcm.py
WrightTools/data/_tensor27.py
WrightTools/data/_variable.py
WrightTools/datasets/__init__.py
WrightTools/datasets/BrunoldrRaman/LDS821_514nm_80mW.txt
WrightTools/datasets/COLORS/v0.2/d1_d2 diagonal.dat
WrightTools/datasets/COLORS/v2.2/WL_wigner.dat
WrightTools/datasets/Cary/CuPCtS_H2O_vis.csv
WrightTools/datasets/Cary/filters.csv
WrightTools/datasets/JASCO/PbSe batch 1.txt
WrightTools/datasets/JASCO/PbSe batch 4 2012-02-21.txt
WrightTools/datasets/JASCO/PbSe batch 4 2012-03-15.txt
WrightTools/datasets/KENT/LDS821 DOVE/w1w2wm_d1eff_3_d2eff_1_LDS_DOVE_Largescan_1
WrightTools/datasets/KENT/LDS821 DOVE/w1w2wm_d1eff_3_d2eff_1_LDS_DOVE_Largescan_10
WrightTools/datasets/KENT/LDS821 DOVE/w1w2wm_d1eff_3_d2eff_1_LDS_DOVE_Largescan_11
wrighttools-3.6.0.dist-info/licenses/LICENSE.txt
wrighttools-3.6.0.dist-info/METADATA
wrighttools-3.6.0.dist-info/WHEEL
wrighttools-3.6.0.dist-info/entry_points.txt
wrighttools-3.6.0.dist-info/top_level.txt
wrighttools-3.6.0.dist-info/RECORD
