Metadata-Version: 2.4
Name: WrightTools
Version: 3.6.0
Summary: Tools for loading, processing, and plotting multidimensional spectroscopy data.
Author: WrightTools Developers
License-Expression: MIT
Project-URL: Homepage, https://github.com/wright-group/WrightTools
Project-URL: Documentation, https://wright.tools
Project-URL: Repository, https://github.com/wright-group/WrightTools.git
Project-URL: Issues, https://github.com/wright-group/WrightTools/issues
Project-URL: Changelog, https://github.com/wright-group/WrightTools/blob/master/CHANGELOG.md
Keywords: spectroscopy,science,multidimensional,visualization
Classifier: Development Status :: 5 - Production/Stable
Classifier: Intended Audience :: Science/Research
Classifier: Framework :: Matplotlib
Classifier: Natural Language :: English
Classifier: Programming Language :: Python :: 3
Classifier: Programming Language :: Python :: 3.11
Classifier: Programming Language :: Python :: 3.12
Classifier: Programming Language :: Python :: 3.13
Classifier: Topic :: Scientific/Engineering
Requires-Python: >=3.7
License-File: LICENSE.txt
Requires-Dist: h5py
Requires-Dist: imageio>=2.28.0
Requires-Dist: matplotlib>=3.4.0
Requires-Dist: numexpr
Requires-Dist: numpy>=1.15.0
Requires-Dist: pint
Requires-Dist: python-dateutil
Requires-Dist: scipy
Requires-Dist: click
Requires-Dist: tidy_headers>=1.0.4
Requires-Dist: rich
Provides-Extra: docs
Requires-Dist: sphinx<8.0; extra == "docs"
Requires-Dist: sphinx-gallery==0.8.2; extra == "docs"
Requires-Dist: sphinx-rtd-theme; extra == "docs"
Provides-Extra: dev
Requires-Dist: black; extra == "dev"
Requires-Dist: pre-commit; extra == "dev"
Requires-Dist: pydocstyle; extra == "dev"
Requires-Dist: pytest; extra == "dev"
Requires-Dist: pytest-cov; extra == "dev"
Requires-Dist: databroker>=1.2; extra == "dev"
Requires-Dist: msgpack; extra == "dev"
Requires-Dist: sphinx<8.0; extra == "dev"
Requires-Dist: sphinx-gallery==0.8.2; extra == "dev"
Requires-Dist: sphinx-rtd-theme; extra == "dev"
Dynamic: license-file
